[
  {
    "id": "resort-kopaonik-rs",
    "name": "Kopaonik",
    "country": "Serbia",
    "region": "Raška",
    "altitude_top": 2017,
    "altitude_base": 1057,
    "vertical_drop": 960,
    "slopes_km": 62,
    "lifts": 25,
    "lat": 43.2858,
    "lng": 20.8085,
    "snowpark": true,
    "night_skiing": true,
    "glacier": false,
    "website": "https://www.skijalistasrbije.rs"
  },
  {
    "id": "resort-stara-planina-rs",
    "name": "Stara Planina",
    "country": "Serbia",
    "region": "Pirot",
    "altitude_top": 2169,
    "altitude_base": 1200,
    "vertical_drop": 969,
    "slopes_km": 13,
    "lifts": 5,
    "lat": 43.3732,
    "lng": 22.6355,
    "snowpark": false,
    "night_skiing": true,
    "glacier": false,
    "website": "https://www.skijalistasrbije.rs"
  },
  {
    "id": "resort-zlatibor-rs",
    "name": "Zlatibor Tornik",
    "country": "Serbia",
    "region": "Zlatibor",
    "altitude_top": 1490,
    "altitude_base": 1110,
    "vertical_drop": 380,
    "slopes_km": 9,
    "lifts": 4,
    "lat": 43.7004,
    "lng": 19.7002,
    "snowpark": true,
    "night_skiing": true,
    "glacier": false,
    "website": "https://www.skijalistasrbije.rs"
  },
  {
    "id": "resort-divcibare-rs",
    "name": "Divčibare",
    "country": "Serbia",
    "region": "Kolubara",
    "altitude_top": 1100,
    "altitude_base": 800,
    "vertical_drop": 300,
    "slopes_km": 4,
    "lifts": 3,
    "lat": 44.1048,
    "lng": 19.9923,
    "snowpark": false,
    "night_skiing": true,
    "glacier": false,
    "website": "https://www.divcibare.rs"
  },
  {
    "id": "resort-goc-rs",
    "name": "Goč",
    "country": "Serbia",
    "region": "Raška",
    "altitude_top": 1123,
    "altitude_base": 750,
    "vertical_drop": 373,
    "slopes_km": 3,
    "lifts": 2,
    "lat": 43.5665,
    "lng": 20.8481,
    "snowpark": false,
    "night_skiing": true,
    "glacier": false,
    "website": "https://goc.rs"
  },
  {
    "id": "resort-besna-kobila-rs",
    "name": "Besna Kobila",
    "country": "Serbia",
    "region": "Pčinja",
    "altitude_top": 1923,
    "altitude_base": 1480,
    "vertical_drop": 443,
    "slopes_km": 5,
    "lifts": 2,
    "lat": 42.6127,
    "lng": 22.2529,
    "snowpark": false,
    "night_skiing": false,
    "glacier": false,
    "website": "https://besnakobila.rs"
  }
]